isitpublic/__init__.py
isitpublic/cache.py
isitpublic/data/about/copyright_terms.json
isitpublic/data/about/historical_works.json
isitpublic/data/about/index.json
isitpublic/data/about/jurisdiction_rules.json
isitpublic/data/about/misconceptions.json
isitpublic/data/about/what_is_pd.json
isitpublic/data/config/copyright_terms.json
isitpublic/data/config/heuristic_indicators.json
isitpublic/data/config/special_rules.json
isitpublic/data/copyright_terms.json
isitpublic/logging.py
isitpublic/matcher.py
isitpublic/models.py
isitpublic/refactored/__init__.py
isitpublic/refactored/analysis/database_rights_analyzer.py
isitpublic/refactored/analysis/decision_tree.py
isitpublic/refactored/analysis/heuristic_analyzer.py
isitpublic/refactored/analysis/performance_rights_analyzer.py
isitpublic/refactored/laws/country_law_manager.py
isitpublic/refactored/main_validator.py
isitpublic/refactored/utils/audit_logger.py
isitpublic/refactored/utils/date_utils.py
isitpublic/refactored/utils/file_handler.py
isitpublic/refactored/utils/result_builder.py
isitpublic/validator.py
isitpublic-0.0.1a7.dist-info/WHEEL
isitpublic-0.0.1a7.dist-info/METADATA
isitpublic-0.0.1a7.dist-info/RECORD
