Metadata-Version: 2.3
Name: isitpublic
Version: 0.0.1a7
Summary: A standalone library for determining if works are likely in the public domain using multiple heuristics and validation methods
Keywords: public domain,copyright,intellectual property,legal,validation,heuristics
Author: WikiReads
Author-email: WikiReads <info@wikireads.org>
License: AGPL-3.0-or-later
Classifier: Development Status :: 4 - Beta
Classifier: Intended Audience :: Developers
Classifier: Intended Audience :: Legal Industry
Classifier: Intended Audience :: Education
Classifier: Topic :: Software Development :: Libraries :: Python Modules
Classifier: Topic :: Utilities
Classifier: License :: OSI Approved :: GNU Affero General Public License v3
Classifier: Programming Language :: Python :: 3
Classifier: Programming Language :: Python :: 3.8
Classifier: Programming Language :: Python :: 3.9
Classifier: Programming Language :: Python :: 3.10
Classifier: Programming Language :: Python :: 3.11
Classifier: Programming Language :: Python :: 3.12
Requires-Dist: pydantic>=2.10.6
Requires-Dist: pydantic-settings>=2.0.0
Requires-Dist: requests>=2.32.4
Requires-Dist: requests-cache>=1.0.0
Requires-Dist: structlog>=25.5.0
Requires-Dist: python-dateutil>=2.8.0
Requires-Dist: pycountry>=22.1.10
Requires-Dist: cachetools>=5.0.0
Requires-Dist: orjson>=3.9.0
Maintainer: WikiReads
Maintainer-email: WikiReads <info@wikireads.org>
Requires-Python: >=3.8
Project-URL: Bug Tracker, https://gitlab.com/ranjithraj/isitpublic/issues
Project-URL: Documentation, https://gitlab.com/ranjithraj/isitpublic#readme
Project-URL: Homepage, https://gitlab.com/ranjithraj/isitpublic
Project-URL: Repository, https://gitlab.com/ranjithraj/isitpublic.git
